gimme_aws_creds/__init__.py
gimme_aws_creds/aws.py
gimme_aws_creds/common.py
gimme_aws_creds/config.py
gimme_aws_creds/default.py
gimme_aws_creds/dummy_webauthn.py
gimme_aws_creds/duo.py
gimme_aws_creds/duo_universal.py
gimme_aws_creds/errors.py
gimme_aws_creds/main.py
gimme_aws_creds/okta_classic.py
gimme_aws_creds/okta_identity_engine.py
gimme_aws_creds/registered_authenticators.py
gimme_aws_creds/u2f.py
gimme_aws_creds/ui.py
gimme_aws_creds/webauthn.py
creds_plz-2.8.3.dist-info/LICENSE
creds_plz-2.8.3.dist-info/METADATA
creds_plz-2.8.3.dist-info/NOTICE
creds_plz-2.8.3.dist-info/WHEEL
creds_plz-2.8.3.dist-info/entry_points.txt
creds_plz-2.8.3.dist-info/top_level.txt
creds_plz-2.8.3.dist-info/RECORD
