Metadata-Version: 2.1
Name: creds-plz
Version: 2.8.3
Summary: A CLI to get temporary AWS credentials from Okta
Home-page: https://github.com/Nike-Inc/gimme-aws-creds
Author: Eric Pierce
Author-email: eric.pierce@nike.com
License: Apache License, v2.0
Classifier: Natural Language :: English
Classifier: Programming Language :: Python :: 3 :: Only
Classifier: License :: OSI Approved :: Apache Software License
Requires-Python: >=3.7
License-File: LICENSE
License-File: NOTICE
Requires-Dist: boto3<2.0.0,>=1.7.70
Requires-Dist: beautifulsoup4<5.0.0,>=4.6.0
Requires-Dist: keyring>=21.4.0
Requires-Dist: requests<3.0.0,>=2.25.0
Requires-Dist: fido2<0.10.0,>=0.9.1
Requires-Dist: okta<3.0.0,>=2.9.0
Requires-Dist: pyjwt<3.0.0,>=2.4.0
Requires-Dist: urllib3<2.0.0,>=1.26.0
Requires-Dist: html5lib<2.0.0,>=1.1
Requires-Dist: furl<3.0.0,>=2.1.3
Requires-Dist: ctap-keyring-device==1.0.6; (sys_platform == "win32" and python_version < "3.10") or sys_platform != "win32"
